ses_verify_identities/__init__.py
ses_verify_identities/py.typed
ses_verify_identities/_jsii/__init__.py
ses_verify_identities/_jsii/ses-verify-identities@4.2.3.jsii.tgz
ses_verify_identities-4.2.3.dist-info/LICENSE
ses_verify_identities-4.2.3.dist-info/METADATA
ses_verify_identities-4.2.3.dist-info/WHEEL
ses_verify_identities-4.2.3.dist-info/top_level.txt
ses_verify_identities-4.2.3.dist-info/RECORD
